pytbx/__init__.py
pytbx/_nbdev.py
pytbx/core.py
pytbx/lp.py
pytbx/settings.py
pytbx-0.0.2.dist-info/LICENSE
pytbx-0.0.2.dist-info/METADATA
pytbx-0.0.2.dist-info/WHEEL
pytbx-0.0.2.dist-info/top_level.txt
pytbx-0.0.2.dist-info/RECORD
