Metadata-Version: 2.1
Name: pytbx
Version: 0.0.2
Summary: A toolbox for my engineering projects.
Home-page: https://gitlab.com/t11c/pytbx/tree/main/
Author: t11c
Author-email: t11c@cvt-engineering.de
License: Apache Software License 2.0
Keywords: engineering
Platform: UNKNOWN
Classifier: Development Status :: 3 - Alpha
Classifier: Intended Audience :: Developers
Classifier: License :: OSI Approved :: Apache Software License
Classifier: Natural Language :: English
Classifier: Programming Language :: Python :: 3.6
Classifier: Programming Language :: Python :: 3.7
Classifier: Programming Language :: Python :: 3.8
Requires-Python: >=3.6
License-File: LICENSE
Requires-Dist: pydantic
